asynchedging/__init__.py
asynchedging/hedge.py
asynchedging-1.0.3.dist-info/METADATA
asynchedging-1.0.3.dist-info/WHEEL
asynchedging-1.0.3.dist-info/licenses/LICENSE
asynchedging-1.0.3.dist-info/RECORD
