Metadata-Version: 2.4
Name: asynchedging
Version: 1.0.3
Summary: Asyncio utilities for racing and hedged requests
Project-URL: Repository, https://github.com/joeyfeldberg/asynchedging
Project-URL: Homepage, https://github.com/joeyfeldberg/asynchedging
Author: Joey Feldberg
License: MIT License
License-File: LICENSE
Requires-Python: >=3.11
